[{"bulletin_id":"WX_20261015_CT_HUB","issued_at":"2026-10-15T00:00:00+07:00","valid_from":"2026-10-15T00:00:00+07:00","valid_to":"2026-10-15T23:00:00+07:00","node_id":"CT_HUB","severity":"none","road_status":"open","water_navigation_status":"open","max_rainfall_mm":9.277847,"max_flood_risk_idx":0.23386,"headline":"Trung tâm trung chuyển Cần Thơ: cảnh báo none, đường bộ thông thường","bulletin_text":"Bản tin mô phỏng cho Trung tâm trung chuyển Cần Thơ ngày 2026-10-15. Mưa cực đại theo giờ 9.3 mm, rủi ro lũ cực đại 0.23. Trạng thái đường bộ: thông thường; trạng thái đường thủy: thông thường. Khi trạng thái là tạm ngưng, agent phải loại tuyến khỏi tập khả thi thay vì chỉ cộng penalty chi phí.","evidence_ref":"weather:2026-10-15:CT_HUB","source_type":"simulated"},{"bulletin_id":"WX_20261015_HCM_MARKET","issued_at":"2026-10-15T00:00:00+07:00","valid_from":"2026-10-15T00:00:00+07:00","valid_to":"2026-10-15T23:00:00+07:00","node_id":"HCM_MARKET","severity":"none","road_status":"open","water_navigation_status":"not_applicable","max_rainfall_mm":8.394242,"max_flood_risk_idx":0.129142,"headline":"Thị trường TP.HCM: cảnh báo none, đường bộ thông thường","bulletin_text":"Bản tin mô phỏng cho Thị trường TP.HCM ngày 2026-10-15. Mưa cực đại theo giờ 8.4 mm, rủi ro lũ cực đại 0.13. Trạng thái đường bộ: thông thường; trạng thái đường thủy: không áp dụng. Khi trạng thái là tạm ngưng, agent phải loại tuyến khỏi tập khả thi thay vì chỉ cộng penalty chi phí.","evidence_ref":"weather:2026-10-15:HCM_MARKET","source_type":"simulated"},{"bulletin_id":"WX_20261015_HUB_LONGXUYEN","issued_at":"2026-10-15T00:00:00+07:00","valid_from":"2026-10-15T00:00:00+07:00","valid_to":"2026-10-15T23:00:00+07:00","node_id":"HUB_LONGXUYEN","severity":"none","road_status":"open","water_navigation_status":"open","max_rainfall_mm":9.012766,"max_flood_risk_idx":0.248477,"headline":"Hub Long Xuyên: cảnh báo none, đường bộ thông thường","bulletin_text":"Bản tin mô phỏng cho Hub Long Xuyên ngày 2026-10-15. Mưa cực đại theo giờ 9.0 mm, rủi ro lũ cực đại 0.25. Trạng thái đường bộ: thông thường; trạng thái đường thủy: thông thường. Khi trạng thái là tạm ngưng, agent phải loại tuyến khỏi tập khả thi thay vì chỉ cộng penalty chi phí.","evidence_ref":"weather:2026-10-15:HUB_LONGXUYEN","source_type":"simulated"},{"bulletin_id":"WX_20261015_HUB_SOCTRANG","issued_at":"2026-10-15T00:00:00+07:00","valid_from":"2026-10-15T00:00:00+07:00","valid_to":"2026-10-15T23:00:00+07:00","node_id":"HUB_SOCTRANG","severity":"none","road_status":"open","water_navigation_status":"open","max_rainfall_mm":9.908556,"max_flood_risk_idx":0.070122,"headline":"Hub Sóc Trăng: cảnh báo none, đường bộ thông thường","bulletin_text":"Bản tin mô phỏng cho Hub Sóc Trăng ngày 2026-10-15. Mưa cực đại theo giờ 9.9 mm, rủi ro lũ cực đại 0.07. Trạng thái đường bộ: thông thường; trạng thái đường thủy: thông thường. Khi trạng thái là tạm ngưng, agent phải loại tuyến khỏi tập khả thi thay vì chỉ cộng penalty chi phí.","evidence_ref":"weather:2026-10-15:HUB_SOCTRANG","source_type":"simulated"},{"bulletin_id":"WX_20261015_HUB_VINHLONG","issued_at":"2026-10-15T00:00:00+07:00","valid_from":"2026-10-15T00:00:00+07:00","valid_to":"2026-10-15T23:00:00+07:00","node_id":"HUB_VINHLONG","severity":"none","road_status":"open","water_navigation_status":"open","max_rainfall_mm":8.841295,"max_flood_risk_idx":0.155414,"headline":"Hub Vĩnh Long: cảnh báo none, đường bộ thông thường","bulletin_text":"Bản tin mô phỏng cho Hub Vĩnh Long ngày 2026-10-15. Mưa cực đại theo giờ 8.8 mm, rủi ro lũ cực đại 0.16. Trạng thái đường bộ: thông thường; trạng thái đường thủy: thông thường. Khi trạng thái là tạm ngưng, agent phải loại tuyến khỏi tập khả thi thay vì chỉ cộng penalty chi phí.","evidence_ref":"weather:2026-10-15:HUB_VINHLONG","source_type":"simulated"},{"bulletin_id":"WX_20261015_HUB_VITHANH","issued_at":"2026-10-15T00:00:00+07:00","valid_from":"2026-10-15T00:00:00+07:00","valid_to":"2026-10-15T23:00:00+07:00","node_id":"HUB_VITHANH","severity":"none","road_status":"open","water_navigation_status":"open","max_rainfall_mm":9.633462,"max_flood_risk_idx":0.12246,"headline":"Hub Vị Thanh: cảnh báo none, đường bộ thông thường","bulletin_text":"Bản tin mô phỏng cho Hub Vị Thanh ngày 2026-10-15. Mưa cực đại theo giờ 9.6 mm, rủi ro lũ cực đại 0.12. Trạng thái đường bộ: thông thường; trạng thái đường thủy: thông thường. Khi trạng thái là tạm ngưng, agent phải loại tuyến khỏi tập khả thi thay vì chỉ cộng penalty chi phí.","evidence_ref":"weather:2026-10-15:HUB_VITHANH","source_type":"simulated"},{"bulletin_id":"WX_20261016_CT_HUB","issued_at":"2026-10-16T00:00:00+07:00","valid_from":"2026-10-16T00:00:00+07:00","valid_to":"2026-10-16T23:00:00+07:00","node_id":"CT_HUB","severity":"none","road_status":"open","water_navigation_status":"open","max_rainfall_mm":11.256412,"max_flood_risk_idx":0.237214,"headline":"Trung tâm trung chuyển Cần Thơ: cảnh báo none, đường bộ thông thường","bulletin_text":"Bản tin mô phỏng cho Trung tâm trung chuyển Cần Thơ ngày 2026-10-16. Mưa cực đại theo giờ 11.3 mm, rủi ro lũ cực đại 0.24. Trạng thái đường bộ: thông thường; trạng thái đường thủy: thông thường. Khi trạng thái là tạm ngưng, agent phải loại tuyến khỏi tập khả thi thay vì chỉ cộng penalty chi phí.","evidence_ref":"weather:2026-10-16:CT_HUB","source_type":"simulated"},{"bulletin_id":"WX_20261016_HCM_MARKET","issued_at":"2026-10-16T00:00:00+07:00","valid_from":"2026-10-16T00:00:00+07:00","valid_to":"2026-10-16T23:00:00+07:00","node_id":"HCM_MARKET","severity":"none","road_status":"open","water_navigation_status":"not_applicable","max_rainfall_mm":10.261246,"max_flood_risk_idx":0.157865,"headline":"Thị trường TP.HCM: cảnh báo none, đường bộ thông thường","bulletin_text":"Bản tin mô phỏng cho Thị trường TP.HCM ngày 2026-10-16. Mưa cực đại theo giờ 10.3 mm, rủi ro lũ cực đại 0.16. Trạng thái đường bộ: thông thường; trạng thái đường thủy: không áp dụng. Khi trạng thái là tạm ngưng, agent phải loại tuyến khỏi tập khả thi thay vì chỉ cộng penalty chi phí.","evidence_ref":"weather:2026-10-16:HCM_MARKET","source_type":"simulated"},{"bulletin_id":"WX_20261016_HUB_LONGXUYEN","issued_at":"2026-10-16T00:00:00+07:00","valid_from":"2026-10-16T00:00:00+07:00","valid_to":"2026-10-16T23:00:00+07:00","node_id":"HUB_LONGXUYEN","severity":"none","road_status":"open","water_navigation_status":"open","max_rainfall_mm":10.934801,"max_flood_risk_idx":0.272261,"headline":"Hub Long Xuyên: cảnh báo none, đường bộ thông thường","bulletin_text":"Bản tin mô phỏng cho Hub Long Xuyên ngày 2026-10-16. Mưa cực đại theo giờ 10.9 mm, rủi ro lũ cực đại 0.27. Trạng thái đường bộ: thông thường; trạng thái đường thủy: thông thường. Khi trạng thái là tạm ngưng, agent phải loại tuyến khỏi tập khả thi thay vì chỉ cộng penalty chi phí.","evidence_ref":"weather:2026-10-16:HUB_LONGXUYEN","source_type":"simulated"},{"bulletin_id":"WX_20261016_HUB_SOCTRANG","issued_at":"2026-10-16T00:00:00+07:00","valid_from":"2026-10-16T00:00:00+07:00","valid_to":"2026-10-16T23:00:00+07:00","node_id":"HUB_SOCTRANG","severity":"none","road_status":"open","water_navigation_status":"open","max_rainfall_mm":12.00684,"max_flood_risk_idx":0.084971,"headline":"Hub Sóc Trăng: cảnh báo none, đường bộ thông thường","bulletin_text":"Bản tin mô phỏng cho Hub Sóc Trăng ngày 2026-10-16. Mưa cực đại theo giờ 12.0 mm, rủi ro lũ cực đại 0.08. Trạng thái đường bộ: thông thường; trạng thái đường thủy: thông thường. Khi trạng thái là tạm ngưng, agent phải loại tuyến khỏi tập khả thi thay vì chỉ cộng penalty chi phí.","evidence_ref":"weather:2026-10-16:HUB_SOCTRANG","source_type":"simulated"},{"bulletin_id":"WX_20261016_HUB_VINHLONG","issued_at":"2026-10-16T00:00:00+07:00","valid_from":"2026-10-16T00:00:00+07:00","valid_to":"2026-10-16T23:00:00+07:00","node_id":"HUB_VINHLONG","severity":"none","road_status":"open","water_navigation_status":"open","max_rainfall_mm":10.987528,"max_flood_risk_idx":0.176591,"headline":"Hub Vĩnh Long: cảnh báo none, đường bộ thông thường","bulletin_text":"Bản tin mô phỏng cho Hub Vĩnh Long ngày 2026-10-16. Mưa cực đại theo giờ 11.0 mm, rủi ro lũ cực đại 0.18. Trạng thái đường bộ: thông thường; trạng thái đường thủy: thông thường. Khi trạng thái là tạm ngưng, agent phải loại tuyến khỏi tập khả thi thay vì chỉ cộng penalty chi phí.","evidence_ref":"weather:2026-10-16:HUB_VINHLONG","source_type":"simulated"},{"bulletin_id":"WX_20261016_HUB_VITHANH","issued_at":"2026-10-16T00:00:00+07:00","valid_from":"2026-10-16T00:00:00+07:00","valid_to":"2026-10-16T23:00:00+07:00","node_id":"HUB_VITHANH","severity":"none","road_status":"open","water_navigation_status":"open","max_rainfall_mm":11.578024,"max_flood_risk_idx":0.125419,"headline":"Hub Vị Thanh: cảnh báo none, đường bộ thông thường","bulletin_text":"Bản tin mô phỏng cho Hub Vị Thanh ngày 2026-10-16. Mưa cực đại theo giờ 11.6 mm, rủi ro lũ cực đại 0.13. Trạng thái đường bộ: thông thường; trạng thái đường thủy: thông thường. Khi trạng thái là tạm ngưng, agent phải loại tuyến khỏi tập khả thi thay vì chỉ cộng penalty chi phí.","evidence_ref":"weather:2026-10-16:HUB_VITHANH","source_type":"simulated"},{"bulletin_id":"WX_20261017_CT_HUB","issued_at":"2026-10-17T00:00:00+07:00","valid_from":"2026-10-17T00:00:00+07:00","valid_to":"2026-10-17T23:00:00+07:00","node_id":"CT_HUB","severity":"none","road_status":"restricted","water_navigation_status":"open","max_rainfall_mm":21.593473,"max_flood_risk_idx":0.296333,"headline":"Trung tâm trung chuyển Cần Thơ: cảnh báo none, đường bộ hạn chế","bulletin_text":"Bản tin mô phỏng cho Trung tâm trung chuyển Cần Thơ ngày 2026-10-17. Mưa cực đại theo giờ 21.6 mm, rủi ro lũ cực đại 0.30. Trạng thái đường bộ: hạn chế; trạng thái đường thủy: thông thường. Khi trạng thái là tạm ngưng, agent phải loại tuyến khỏi tập khả thi thay vì chỉ cộng penalty chi phí.","evidence_ref":"weather:2026-10-17:CT_HUB","source_type":"simulated"},{"bulletin_id":"WX_20261017_HCM_MARKET","issued_at":"2026-10-17T00:00:00+07:00","valid_from":"2026-10-17T00:00:00+07:00","valid_to":"2026-10-17T23:00:00+07:00","node_id":"HCM_MARKET","severity":"none","road_status":"restricted","water_navigation_status":"not_applicable","max_rainfall_mm":19.51163,"max_flood_risk_idx":0.300179,"headline":"Thị trường TP.HCM: cảnh báo none, đường bộ hạn chế","bulletin_text":"Bản tin mô phỏng cho Thị trường TP.HCM ngày 2026-10-17. Mưa cực đại theo giờ 19.5 mm, rủi ro lũ cực đại 0.30. Trạng thái đường bộ: hạn chế; trạng thái đường thủy: không áp dụng. Khi trạng thái là tạm ngưng, agent phải loại tuyến khỏi tập khả thi thay vì chỉ cộng penalty chi phí.","evidence_ref":"weather:2026-10-17:HCM_MARKET","source_type":"simulated"},{"bulletin_id":"WX_20261017_HUB_LONGXUYEN","issued_at":"2026-10-17T00:00:00+07:00","valid_from":"2026-10-17T00:00:00+07:00","valid_to":"2026-10-17T23:00:00+07:00","node_id":"HUB_LONGXUYEN","severity":"watch","road_status":"restricted","water_navigation_status":"open","max_rainfall_mm":20.925562,"max_flood_risk_idx":0.350942,"headline":"Hub Long Xuyên: cảnh báo watch, đường bộ hạn chế","bulletin_text":"Bản tin mô phỏng cho Hub Long Xuyên ngày 2026-10-17. Mưa cực đại theo giờ 20.9 mm, rủi ro lũ cực đại 0.35. Trạng thái đường bộ: hạn chế; trạng thái đường thủy: thông thường. Khi trạng thái là tạm ngưng, agent phải loại tuyến khỏi tập khả thi thay vì chỉ cộng penalty chi phí.","evidence_ref":"weather:2026-10-17:HUB_LONGXUYEN","source_type":"simulated"},{"bulletin_id":"WX_20261017_HUB_SOCTRANG","issued_at":"2026-10-17T00:00:00+07:00","valid_from":"2026-10-17T00:00:00+07:00","valid_to":"2026-10-17T23:00:00+07:00","node_id":"HUB_SOCTRANG","severity":"none","road_status":"open","water_navigation_status":"open","max_rainfall_mm":22.992782,"max_flood_risk_idx":0.162718,"headline":"Hub Sóc Trăng: cảnh báo none, đường bộ thông thường","bulletin_text":"Bản tin mô phỏng cho Hub Sóc Trăng ngày 2026-10-17. Mưa cực đại theo giờ 23.0 mm, rủi ro lũ cực đại 0.16. Trạng thái đường bộ: thông thường; trạng thái đường thủy: thông thường. Khi trạng thái là tạm ngưng, agent phải loại tuyến khỏi tập khả thi thay vì chỉ cộng penalty chi phí.","evidence_ref":"weather:2026-10-17:HUB_SOCTRANG","source_type":"simulated"},{"bulletin_id":"WX_20261017_HUB_VINHLONG","issued_at":"2026-10-17T00:00:00+07:00","valid_from":"2026-10-17T00:00:00+07:00","valid_to":"2026-10-17T23:00:00+07:00","node_id":"HUB_VINHLONG","severity":"none","road_status":"open","water_navigation_status":"open","max_rainfall_mm":20.507451,"max_flood_risk_idx":0.248273,"headline":"Hub Vĩnh Long: cảnh báo none, đường bộ thông thường","bulletin_text":"Bản tin mô phỏng cho Hub Vĩnh Long ngày 2026-10-17. Mưa cực đại theo giờ 20.5 mm, rủi ro lũ cực đại 0.25. Trạng thái đường bộ: thông thường; trạng thái đường thủy: thông thường. Khi trạng thái là tạm ngưng, agent phải loại tuyến khỏi tập khả thi thay vì chỉ cộng penalty chi phí.","evidence_ref":"weather:2026-10-17:HUB_VINHLONG","source_type":"simulated"},{"bulletin_id":"WX_20261017_HUB_VITHANH","issued_at":"2026-10-17T00:00:00+07:00","valid_from":"2026-10-17T00:00:00+07:00","valid_to":"2026-10-17T23:00:00+07:00","node_id":"HUB_VITHANH","severity":"none","road_status":"open","water_navigation_status":"open","max_rainfall_mm":22.330665,"max_flood_risk_idx":0.205352,"headline":"Hub Vị Thanh: cảnh báo none, đường bộ thông thường","bulletin_text":"Bản tin mô phỏng cho Hub Vị Thanh ngày 2026-10-17. Mưa cực đại theo giờ 22.3 mm, rủi ro lũ cực đại 0.21. Trạng thái đường bộ: thông thường; trạng thái đường thủy: thông thường. Khi trạng thái là tạm ngưng, agent phải loại tuyến khỏi tập khả thi thay vì chỉ cộng penalty chi phí.","evidence_ref":"weather:2026-10-17:HUB_VITHANH","source_type":"simulated"}]
